genai_processors_url_fetch/__init__.py
genai_processors_url_fetch/url_fetch.py
genai_processors_url_fetch/tests/__init__.py
genai_processors_url_fetch/tests/test_markitdown.py
genai_processors_url_fetch/tests/test_url_fetch.py
genai_processors_url_fetch-0.3.2.dist-info/METADATA
genai_processors_url_fetch-0.3.2.dist-info/WHEEL
genai_processors_url_fetch-0.3.2.dist-info/licenses/LICENSE
genai_processors_url_fetch-0.3.2.dist-info/RECORD
