Metadata-Version: 2.4
Name: genai-processors-url-fetch
Version: 0.3.2
Summary: A URL fetch processor for Google's genai-processors framework
Project-URL: Homepage, https://github.com/mbeacom/genai-processors-url-fetch
Project-URL: Repository, https://github.com/mbeacom/genai-processors-url-fetch.git
Project-URL: Issues, https://github.com/mbeacom/genai-processors-url-fetch/issues
Project-URL: Documentation, https://github.com/mbeacom/genai-processors-url-fetch#readme
Author-email: Mark Beacom <m@beacom.dev>
License: Apache-2.0
License-File: LICENSE
Keywords: ai,contrib,deepmind,fetch,gemini,genai,genai-processors,genai-processors-contrib,generative-ai,google,http,processor,processors,schema,url,validation
Classifier: Development Status :: 4 - Beta
Classifier: Intended Audience :: Developers
Classifier: License :: OSI Approved :: Apache Software License
Classifier: Operating System :: OS Independent
Classifier: Programming Language :: Python
Classifier: Programming Language :: Python :: 3
Classifier: Programming Language :: Python :: 3.11
Classifier: Programming Language :: Python :: 3.12
Classifier: Programming Language :: Python :: 3.13
Classifier: Topic :: Scientific/Engineering :: Artificial Intelligence
Classifier: Topic :: Software Development :: Libraries :: Python Modules
Requires-Python: >=3.11
Requires-Dist: beautifulsoup4>=4.13.0
Requires-Dist: genai-processors>=1.0.4
Requires-Dist: httpx>=0.28.0
Provides-Extra: all
Requires-Dist: markitdown>=0.1.2; extra == 'all'
Provides-Extra: markitdown
Requires-Dist: markitdown>=0.1.2; extra == 'markitdown'
